codehacks/__init__.py
codehacks-0.1.dist-info/METADATA
codehacks-0.1.dist-info/WHEEL
codehacks-0.1.dist-info/top_level.txt
codehacks-0.1.dist-info/RECORD
