Metadata-Version: 2.1
Name: codehacks
Version: 0.1
Summary: this is very basic calculator
Author: charu garg
Author-email: gargcharu59@gmail.com
Classifier: Programming Language :: Python :: 3
Classifier: License :: OSI Approved :: MIT License
Classifier: Operating System :: OS Independent
